pkg2/__init__.py
pkg2/module1.py
pkg3/__init__.py
pkg3/module1.py
pkg1-0.0.3.dist-info/METADATA
pkg1-0.0.3.dist-info/WHEEL
pkg1-0.0.3.dist-info/top_level.txt
pkg1-0.0.3.dist-info/RECORD
