Metadata-Version: 1.2
Name: pkg1
Version: 0.0.3
Summary: A daily useful kit by Hong Peng.
Home-page: https://github.com/zhengxingyu/hpkit.git
Author: zhengxingyu
License: MIT
Platform: UNKNOWN
Requires-Python: >=3.6.0
